{
  "project_info": {
    "project_number": "470278129082",
    "project_id": "emra-d0269",
    "storage_bucket": "emra-d0269.appspot.com"
  },
  "client": [
    {
      "client_info": {
        "mobilesdk_app_id": "1:470278129082:android:0f70d0a0ac400d41828983",
        "android_client_info": {
          "package_name": "com.example.emergency_app"
        }
      },
      "oauth_client": [],
      "api_key": [
        {
          "current_key": "AIzaSyAY-tJ7hlHn1priRALZVPkjm0tqDrq0S6g"
        }
      ],
      "services": {
        "appinvite_service": {
          "other_platform_oauth_client": []
        }
      }
    }
  ],
  "configuration_version": "1"
}